pqmarkup.py
syntax_highlighter_for_pqmarkup.py
pqmarkup-2022.11.dist-info/LICENSE.txt
pqmarkup-2022.11.dist-info/METADATA
pqmarkup-2022.11.dist-info/WHEEL
pqmarkup-2022.11.dist-info/top_level.txt
pqmarkup-2022.11.dist-info/RECORD
