Metadata-Version: 2.1
Name: pqmarkup
Version: 2022.11
Summary: A Python implementation of pq markup to HTML converter.
Home-page: http://pqmarkup.org
Author: Alexander Tretyak
Author-email: pqmarkup@gmail.com
License: BSD
Download-URL: https://sourceforge.net/p/pqmarkup/code/ci/default/tarball
Platform: UNKNOWN
Classifier: Development Status :: 5 - Production/Stable
Classifier: Operating System :: OS Independent
Classifier: Programming Language :: Python :: 3
Classifier: License :: OSI Approved :: BSD License
Classifier: Topic :: Text Processing :: Markup :: HTML
